otto_m8/core/config.py
otto_m8/run.py
otto_m8-0.0.2.dist-info/LICENSE
otto_m8-0.0.2.dist-info/METADATA
otto_m8-0.0.2.dist-info/WHEEL
otto_m8-0.0.2.dist-info/RECORD
