Metadata-Version: 2.3
Name: otto-m8
Version: 0.0.2
Summary: Python SDK for otto-m8, a low code tool to build and deploy AI/ML workloads.
License: Apache-2.0
Author: farhan0167
Author-email: afi225@nyu.edu
Requires-Python: >=3.11,<3.13
Classifier: License :: OSI Approved :: Apache Software License
Classifier: Programming Language :: Python :: 3
Classifier: Programming Language :: Python :: 3.11
Classifier: Programming Language :: Python :: 3.12
Requires-Dist: otto-m8-backend (==0.1.0)
